{
    "items": [
        {
            "owner": {
                "reputation": 3698,
                "user_id": 2470765,
                "user_type": "registered",
                "accept_rate": 59,
                "profile_image": "https://i.stack.imgur.com/DOj3z.jpg?s=128&g=1",
                "display_name": "michal.jakubeczy",
                "link": "https://stackoverflow.com/users/2470765/michal-jakubeczy"
            },
            "is_accepted": false,
            "score": 0,
            "last_activity_date": 1606476887,
            "creation_date": 1606476887,
            "answer_id": 65036678,
            "question_id": 41757261,
            "content_license": "CC BY-SA 4.0"
        },
        {
            "owner": {
                "reputation": 668,
                "user_id": 2952185,
                "user_type": "registered",
                "profile_image": "https://www.gravatar.com/avatar/d33ca05ba46e39cbe0bc0923a5ac4071?s=128&d=identicon&r=PG",
                "display_name": "Gijs Wobben",
                "link": "https://stackoverflow.com/users/2952185/gijs-wobben"
            },
            "is_accepted": false,
            "score": 0,
            "last_activity_date": 1606476883,
            "creation_date": 1606476883,
            "answer_id": 65036677,
            "question_id": 65010925,
            "content_license": "CC BY-SA 4.0"
        },
        {
            "owner": {
                "reputation": 79,
                "user_id": 5652480,
                "user_type": "registered",
                "profile_image": "https://i.stack.imgur.com/bREne.jpg?s=128&g=1",
                "display_name": "willcrack",
                "link": "https://stackoverflow.com/users/5652480/willcrack"
            },
            "is_accepted": false,
            "score": 0,
            "last_activity_date": 1606476864,
            "creation_date": 1606476864,
            "answer_id": 65036674,
            "question_id": 65036138,
            "content_license": "CC BY-SA 4.0"
        },
        {
            "owner": {
                "reputation": 10391,
                "user_id": 4393565,
                "user_type": "registered",
                "accept_rate": 67,
                "profile_image": "https://www.gravatar.com/avatar/19ab0903bafafe65cabf872f3ef5cff6?s=128&d=identicon&r=PG",
                "display_name": "P.J.Meisch",
                "link": "https://stackoverflow.com/users/4393565/p-j-meisch"
            },
            "is_accepted": false,
            "score": 0,
            "last_activity_date": 1606476851,
            "creation_date": 1606476851,
            "answer_id": 65036671,
            "question_id": 65028059,
            "content_license": "CC BY-SA 4.0"
        },
        {
            "owner": {
                "reputation": 82840,
                "user_id": 134204,
                "user_type": "registered",
                "profile_image": "https://i.stack.imgur.com/vwnA5.jpg?s=128&g=1",
                "display_name": "Panagiotis Kanavos",
                "link": "https://stackoverflow.com/users/134204/panagiotis-kanavos"
            },
            "is_accepted": true,
            "score": 43,
            "last_activity_date": 1606476834,
            "last_edit_date": 1606476834,
            "creation_date": 1423729286,
            "answer_id": 28472505,
            "question_id": 28472205,
            "content_license": "CC BY-SA 4.0"
        },
        {
            "owner": {
                "reputation": 4987,
                "user_id": 5644961,
                "user_type": "registered",
                "accept_rate": 100,
                "profile_image": "https://lh5.googleusercontent.com/-r4jx_ltcdtA/AAAAAAAAAAI/AAAAAAAAAAA/7RjDfLKZHxg/photo.jpg?sz=128",
                "display_name": "Copperfield",
                "link": "https://stackoverflow.com/users/5644961/copperfield"
            },
            "is_accepted": false,
            "score": 1,
            "last_activity_date": 1606476833,
            "last_edit_date": 1606476833,
            "creation_date": 1606450024,
            "answer_id": 65031968,
            "question_id": 65031581,
            "content_license": "CC BY-SA 4.0"
        },
        {
            "owner": {
                "reputation": 19,
                "user_id": 7342741,
                "user_type": "registered",
                "profile_image": "https://i.stack.imgur.com/n6clp.png?s=128&g=1",
                "display_name": "Masterhaend",
                "link": "https://stackoverflow.com/users/7342741/masterhaend"
            },
            "is_accepted": false,
            "score": 0,
            "last_activity_date": 1606476828,
            "creation_date": 1606476828,
            "answer_id": 65036668,
            "question_id": 65036389,
            "content_license": "CC BY-SA 4.0"
        },
        {
            "owner": {
                "reputation": 86,
                "user_id": 11429027,
                "user_type": "registered",
                "profile_image": "https://i.stack.imgur.com/90zFm.jpg?s=128&g=1",
                "display_name": "David Stania",
                "link": "https://stackoverflow.com/users/11429027/david-stania"
            },
            "is_accepted": false,
            "score": 0,
            "last_activity_date": 1606476824,
            "last_edit_date": 1606476824,
            "creation_date": 1606476521,
            "answer_id": 65036610,
            "question_id": 65035431,
            "content_license": "CC BY-SA 4.0"
        },
        {
            "owner": {
                "reputation": 4792,
                "user_id": 4653172,
                "user_type": "registered",
                "profile_image": "https://www.gravatar.com/avatar/3c894c1021e3092a98cdd62d88e69819?s=128&d=identicon&r=PG&f=1",
                "display_name": "Jerzy D.",
                "link": "https://stackoverflow.com/users/4653172/jerzy-d"
            },
            "is_accepted": false,
            "score": 0,
            "last_activity_date": 1606476805,
            "creation_date": 1606476805,
            "answer_id": 65036663,
            "question_id": 65015631,
            "content_license": "CC BY-SA 4.0"
        },
        {
            "owner": {
                "reputation": 206664,
                "user_id": 2877241,
                "user_type": "registered",
                "accept_rate": 52,
                "profile_image": "https://www.gravatar.com/avatar/63d17ecdadc8917254be4fb70e86246b?s=128&d=identicon&r=PG&f=1",
                "display_name": "Vlad from Moscow",
                "link": "https://stackoverflow.com/users/2877241/vlad-from-moscow"
            },
            "is_accepted": false,
            "score": 0,
            "last_activity_date": 1606476792,
            "creation_date": 1606476792,
            "answer_id": 65036661,
            "question_id": 65036639,
            "content_license": "CC BY-SA 4.0"
        },
        {
            "owner": {
                "reputation": 19228,
                "user_id": 1784011,
                "user_type": "registered",
                "accept_rate": 100,
                "profile_image": "https://i.stack.imgur.com/5QrkA.png?s=128&g=1",
                "display_name": "Woodstock",
                "link": "https://stackoverflow.com/users/1784011/woodstock"
            },
            "is_accepted": true,
            "score": 4,
            "last_activity_date": 1606476789,
            "last_edit_date": 1606476789,
            "creation_date": 1578481194,
            "answer_id": 59644375,
            "question_id": 59641986,
            "content_license": "CC BY-SA 4.0"
        },
        {
            "owner": {
                "reputation": 235895,
                "user_id": 2422776,
                "user_type": "registered",
                "profile_image": "https://www.gravatar.com/avatar/2353050223ebecb113741c29458de4b2?s=128&d=identicon&r=PG",
                "display_name": "Mureinik",
                "link": "https://stackoverflow.com/users/2422776/mureinik"
            },
            "is_accepted": false,
            "score": 0,
            "last_activity_date": 1606476785,
            "creation_date": 1606476785,
            "answer_id": 65036659,
            "question_id": 65036587,
            "content_license": "CC BY-SA 4.0"
        },
        {
            "owner": {
                "reputation": 344,
                "user_id": 4818970,
                "user_type": "registered",
                "profile_image": "https://i.stack.imgur.com/B2zEW.png?s=128&g=1",
                "display_name": "GnRSlashSP",
                "link": "https://stackoverflow.com/users/4818970/gnrslashsp"
            },
            "is_accepted": false,
            "score": 0,
            "last_activity_date": 1606476783,
            "creation_date": 1606476783,
            "answer_id": 65036658,
            "question_id": 64319807,
            "content_license": "CC BY-SA 4.0"
        },
        {
            "owner": {
                "reputation": 103,
                "user_id": 11043336,
                "user_type": "registered",
                "profile_image": "https://lh3.googleusercontent.com/-Fs8igczewZI/AAAAAAAAAAI/AAAAAAAADuk/kWORR-B2Hf8/photo.jpg?sz=128",
                "display_name": "Алексей Семенов",
                "link": "https://stackoverflow.com/users/11043336/%d0%90%d0%bb%d0%b5%d0%ba%d1%81%d0%b5%d0%b9-%d0%a1%d0%b5%d0%bc%d0%b5%d0%bd%d0%be%d0%b2"
            },
            "is_accepted": false,
            "score": 0,
            "last_activity_date": 1606476783,
            "last_edit_date": 1606476783,
            "creation_date": 1606476186,
            "answer_id": 65036534,
            "question_id": 65036324,
            "content_license": "CC BY-SA 4.0"
        },
        {
            "owner": {
                "reputation": 3037,
                "user_id": 6167440,
                "user_type": "registered",
                "accept_rate": 100,
                "profile_image": "https://www.gravatar.com/avatar/058051f8cb05e24aefbb72e0269a1349?s=128&d=identicon&r=PG&f=1",
                "display_name": "Tyron78",
                "link": "https://stackoverflow.com/users/6167440/tyron78"
            },
            "is_accepted": false,
            "score": 0,
            "last_activity_date": 1606476772,
            "creation_date": 1606476772,
            "answer_id": 65036656,
            "question_id": 64000737,
            "content_license": "CC BY-SA 4.0"
        },
        {
            "owner": {
                "reputation": 15545,
                "user_id": 427292,
                "user_type": "registered",
                "accept_rate": 86,
                "profile_image": "https://www.gravatar.com/avatar/b560f3cb49b191dd5cea75cd739c18e8?s=128&d=identicon&r=PG",
                "display_name": "Josh Kahane",
                "link": "https://stackoverflow.com/users/427292/josh-kahane"
            },
            "is_accepted": false,
            "score": 0,
            "last_activity_date": 1606476769,
            "creation_date": 1606476769,
            "answer_id": 65036653,
            "question_id": 64928557,
            "content_license": "CC BY-SA 4.0"
        },
        {
            "owner": {
                "reputation": 323,
                "user_id": 2231652,
                "user_type": "registered",
                "profile_image": "https://www.gravatar.com/avatar/bccd8a27bbf77651c3ad812e55df4a60?s=128&d=identicon&r=PG",
                "display_name": "Istv&#225;n Pat&#243;",
                "link": "https://stackoverflow.com/users/2231652/istv%c3%a1n-pat%c3%b3"
            },
            "is_accepted": false,
            "score": 0,
            "last_activity_date": 1606476766,
            "creation_date": 1606476766,
            "answer_id": 65036652,
            "question_id": 23215227,
            "content_license": "CC BY-SA 4.0"
        },
        {
            "owner": {
                "reputation": 90,
                "user_id": 10992464,
                "user_type": "registered",
                "profile_image": "https://i.stack.imgur.com/wF8M8.jpg?s=128&g=1",
                "display_name": "tibetiroka",
                "link": "https://stackoverflow.com/users/10992464/tibetiroka"
            },
            "is_accepted": false,
            "score": 0,
            "last_activity_date": 1606476761,
            "creation_date": 1606476761,
            "answer_id": 65036651,
            "question_id": 65036389,
            "content_license": "CC BY-SA 4.0"
        },
        {
            "owner": {
                "reputation": 2101,
                "user_id": 6952359,
                "user_type": "registered",
                "accept_rate": 100,
                "profile_image": "https://i.stack.imgur.com/LefS5.png?s=128&g=1",
                "display_name": "Harshana Serasinghe",
                "link": "https://stackoverflow.com/users/6952359/harshana-serasinghe"
            },
            "is_accepted": false,
            "score": 0,
            "last_activity_date": 1606476718,
            "creation_date": 1606476718,
            "answer_id": 65036644,
            "question_id": 65036432,
            "content_license": "CC BY-SA 4.0"
        },
        {
            "owner": {
                "reputation": 17,
                "user_id": 10349759,
                "user_type": "registered",
                "profile_image": "https://lh4.googleusercontent.com/-4KfcfkRby7U/AAAAAAAAAAI/AAAAAAAAAAc/WBiVnpTha0M/photo.jpg?sz=128",
                "display_name": "Aman Agrawal",
                "link": "https://stackoverflow.com/users/10349759/aman-agrawal"
            },
            "is_accepted": false,
            "score": 0,
            "last_activity_date": 1606476711,
            "last_edit_date": 1606476711,
            "creation_date": 1606379072,
            "answer_id": 65018383,
            "question_id": 64985192,
            "content_license": "CC BY-SA 4.0"
        },
        {
            "owner": {
                "reputation": 1029,
                "user_id": 14521257,
                "user_type": "registered",
                "profile_image": "https://www.gravatar.com/avatar/ba386cca15254dbc3b62558ea32dd225?s=128&d=identicon&r=PG",
                "display_name": "ozgur",
                "link": "https://stackoverflow.com/users/14521257/ozgur"
            },
            "is_accepted": true,
            "score": 1,
            "last_activity_date": 1606476702,
            "last_edit_date": 1606476702,
            "creation_date": 1606377371,
            "answer_id": 65017985,
            "question_id": 65017631,
            "content_license": "CC BY-SA 4.0"
        },
        {
            "owner": {
                "reputation": 534,
                "user_id": 5342020,
                "user_type": "registered",
                "profile_image": "https://www.gravatar.com/avatar/a40329a95178fe7cb3e62ae6f0ffedeb?s=128&d=identicon&r=PG&f=1",
                "display_name": "Marcin Mrugas",
                "link": "https://stackoverflow.com/users/5342020/marcin-mrugas"
            },
            "is_accepted": true,
            "score": 1,
            "last_activity_date": 1606476695,
            "last_edit_date": 1606476695,
            "creation_date": 1606474325,
            "answer_id": 65036100,
            "question_id": 65035844,
            "content_license": "CC BY-SA 4.0"
        },
        {
            "owner": {
                "reputation": 1,
                "user_id": 12958219,
                "user_type": "registered",
                "profile_image": "https://lh6.googleusercontent.com/-xJJM5vx5d5Y/AAAAAAAAAAI/AAAAAAAAAAA/ACHi3rc8n2Sgf_XSrAQeU6dJ83wdIVbeqw/photo.jpg?sz=128",
                "display_name": "Shawn Shivere",
                "link": "https://stackoverflow.com/users/12958219/shawn-shivere"
            },
            "is_accepted": false,
            "score": 0,
            "last_activity_date": 1606476694,
            "creation_date": 1606476694,
            "answer_id": 65036637,
            "question_id": 59601416,
            "content_license": "CC BY-SA 4.0"
        },
        {
            "owner": {
                "reputation": 235,
                "user_id": 10874806,
                "user_type": "registered",
                "profile_image": "https://lh3.googleusercontent.com/-FkDdxV2655w/AAAAAAAAAAI/AAAAAAAAAFs/FLbfNwzOmjE/photo.jpg?sz=128",
                "display_name": "Hamza Khattabi",
                "link": "https://stackoverflow.com/users/10874806/hamza-khattabi"
            },
            "is_accepted": false,
            "score": 3,
            "last_activity_date": 1606476687,
            "last_edit_date": 1606476687,
            "creation_date": 1606476243,
            "answer_id": 65036547,
            "question_id": 65036377,
            "content_license": "CC BY-SA 4.0"
        },
        {
            "owner": {
                "reputation": 32100,
                "user_id": 1898563,
                "user_type": "registered",
                "accept_rate": 78,
                "profile_image": "https://www.gravatar.com/avatar/d99204bcce923f40f5c72b7f80121644?s=128&d=identicon&r=PG",
                "display_name": "Michael",
                "link": "https://stackoverflow.com/users/1898563/michael"
            },
            "is_accepted": false,
            "score": 1,
            "last_activity_date": 1606476669,
            "last_edit_date": 1606476669,
            "creation_date": 1606474773,
            "answer_id": 65036202,
            "question_id": 65034312,
            "content_license": "CC BY-SA 4.0"
        },
        {
            "owner": {
                "reputation": 24534,
                "user_id": 5320906,
                "user_type": "registered",
                "profile_image": "https://i.stack.imgur.com/NOdNo.jpg?s=128&g=1",
                "display_name": "snakecharmerb",
                "link": "https://stackoverflow.com/users/5320906/snakecharmerb"
            },
            "is_accepted": false,
            "score": 0,
            "last_activity_date": 1606476661,
            "creation_date": 1606476661,
            "answer_id": 65036635,
            "question_id": 65034969,
            "content_license": "CC BY-SA 4.0"
        },
        {
            "owner": {
                "reputation": 16752,
                "user_id": 11599789,
                "user_type": "registered",
                "profile_image": "https://i.stack.imgur.com/1l1AT.jpg?s=128&g=1",
                "display_name": "ziganotschka",
                "link": "https://stackoverflow.com/users/11599789/ziganotschka"
            },
            "is_accepted": false,
            "score": 0,
            "last_activity_date": 1606476620,
            "creation_date": 1606476620,
            "answer_id": 65036630,
            "question_id": 65035835,
            "content_license": "CC BY-SA 4.0"
        },
        {
            "owner": {
                "reputation": 3041,
                "user_id": 10659482,
                "user_type": "registered",
                "profile_image": "https://lh3.googleusercontent.com/-6gY6xz9NZX0/AAAAAAAAAAI/AAAAAAAAGK0/unNDWBQf9v4/photo.jpg?sz=128",
                "display_name": "Akif",
                "link": "https://stackoverflow.com/users/10659482/akif"
            },
            "is_accepted": false,
            "score": 0,
            "last_activity_date": 1606476614,
            "creation_date": 1606476614,
            "answer_id": 65036629,
            "question_id": 65036583,
            "content_license": "CC BY-SA 4.0"
        },
        {
            "owner": {
                "reputation": 419,
                "user_id": 8155208,
                "user_type": "registered",
                "profile_image": "https://lh3.googleusercontent.com/-qg0fwAawlXE/AAAAAAAAAAI/AAAAAAAAE5o/-tr_sIjsjCA/photo.jpg?sz=128",
                "display_name": "Ashu",
                "link": "https://stackoverflow.com/users/8155208/ashu"
            },
            "is_accepted": false,
            "score": -1,
            "last_activity_date": 1606476596,
            "creation_date": 1606476596,
            "answer_id": 65036626,
            "question_id": 65036543,
            "content_license": "CC BY-SA 4.0"
        },
        {
            "owner": {
                "reputation": 181946,
                "user_id": 575376,
                "user_type": "registered",
                "accept_rate": 82,
                "profile_image": "https://i.stack.imgur.com/soXsL.gif?s=128&g=1",
                "display_name": "juergen d",
                "link": "https://stackoverflow.com/users/575376/juergen-d"
            },
            "is_accepted": false,
            "score": 0,
            "last_activity_date": 1606476587,
            "last_edit_date": 1606476587,
            "creation_date": 1606476454,
            "answer_id": 65036592,
            "question_id": 65036574,
            "content_license": "CC BY-SA 4.0"
        }
    ],
    "has_more": true,
    "backoff": 10,
    "quota_max": 10000,
    "quota_remaining": 9942
}